CHANGELOG.txt
LICENSE.txt
MANIFEST.in
README.txt
setup.py
quicksetup/__init__.py
quicksetup.egg-info/PKG-INFO
quicksetup.egg-info/SOURCES.txt
quicksetup.egg-info/dependency_links.txt
quicksetup.egg-info/requires.txt
quicksetup.egg-info/top_level.txt